findfaces/__init__.py
findfaces/face_detector_image.py
findfaces/face_detector_video.py
findfaces/tool.py
findfaces/tools.py
findfaces/images/img01.jpg
findfaces/images/img02.jpg
findfaces/images/img03.jpg
findfaces/images/img04.jpg
findfaces/images/img05.jpg
findfaces/images/img06.jpg
findfaces/images/img07.jpg
findfaces/images/img08.jpg
findfaces/images/img09.jpg
findfaces/images/img10.jpg
findfaces/images/img11.jpg
findfaces/images/img12.jpg
findfaces/images/img13.jpg
findfaces/images/img14.jpg
findfaces/images/img16.jpg
findfaces/images/img17.jpg
findfaces/images/img18.jpg
findfaces/images/img19.jpg
findfaces/images/img20.jpg
findfaces/models/deploy.prototxt.txt
findfaces/models/image_face_detection.txt
findfaces/models/res10_300x300_ssd_iter_140000.caffemodel
findfaces-0.0.2.data/scripts/ff_cropAllFaces
findfaces-0.0.2.data/scripts/ff_cropAllFaces.cmd
findfaces-0.0.2.data/scripts/ff_detect
findfaces-0.0.2.data/scripts/ff_detect.cmd
findfaces-0.0.2.data/scripts/ff_help
findfaces-0.0.2.data/scripts/ff_help.cmd
findfaces-0.0.2.dist-info/DESCRIPTION.rst
findfaces-0.0.2.dist-info/METADATA
findfaces-0.0.2.dist-info/RECORD
findfaces-0.0.2.dist-info/WHEEL
findfaces-0.0.2.dist-info/metadata.json
findfaces-0.0.2.dist-info/top_level.txt
