Metadata-Version: 2.0
Name: findfaces
Version: 0.0.2
Summary: Python library for find faces.
Home-page: https://github.com/tuaplicacionpropia/findfaces
Author: tuaplicacionpropia.com
Author-email: tuaplicacionpropia@gmail.com
License: MIT
Download-URL: https://github.com/tuaplicacionpropia/findfaces/archive/master.zip
Keywords: faces,detect,dnn,opencv
Platform: any
Classifier: Development Status :: 4 - Beta
Classifier: License :: OSI Approved :: MIT License
Classifier: Programming Language :: Python
Classifier: Programming Language :: Python :: 2.7
Classifier: Intended Audience :: Developers
Classifier: Topic :: Multimedia :: Graphics
Requires-Dist: numpy (>=1.12.0)
Requires-Dist: opencv-python (>=3.1.0.3)
Requires-Dist: screeninfo (>=0.3.1)
